quickdb/__init__.py
quickdb/cli.py
quickdb/main.py
stock_dashboard-0.0.1.dist-info/LICENSE
stock_dashboard-0.0.1.dist-info/METADATA
stock_dashboard-0.0.1.dist-info/WHEEL
stock_dashboard-0.0.1.dist-info/entry_points.txt
stock_dashboard-0.0.1.dist-info/top_level.txt
stock_dashboard-0.0.1.dist-info/RECORD
